{
  "title": "Awesome OpenClaw Tutorial",
  "description": "龙虾 OpenClaw 中文教程：大龙虾 Claw 从零到上手，含安装配置、飞书/企微接入、Skills 扩展、文件与知识库管理、自动化工作流与 70+ 实战案例，最全 OpenClaw 指南。",
  "url": "",
  "baseurl": "",
  "repository": "fds2003/awesome-openclaw",
  "keywords": "龙虾, 大龙虾, claw, openclaw, OpenClaw, OpenClaw教程, 龙虾教程, AI助手, 飞书机器人, 飞书Bot, Skills, Gateway, ClawHub, 安装配置, 快速上手, 文件管理, 知识库, 日程管理, 自动化工作流, 多平台集成, 企微, 钉钉, API集成, 命令速查, 实战案例, 超级个体, 中文教程",
  "lang": "zh-CN",
  "locale": "zh_CN",
  "navigation": [
    { "title": "首页", "url": "/" },
    { "title": "快速开始", "url": "/docs/01-basics/03-quick-start/" },
    { "title": "核心功能", "url": "/docs/02-core-features/04-file-management/" },
    { "title": "进阶应用", "url": "/docs/03-advanced/08-skills-extension/" },
    { "title": "实战案例", "url": "/docs/04-practical-cases/12-personal-productivity/" },
    { "title": "附录", "url": "/appendix/A-command-reference/" }
  ]
}
